torch_so3/__init__.py
torch_so3/angular_ranges.py
torch_so3/base_s2_grid.py
torch_so3/local_so3_sampling.py
torch_so3/uniform_so3_sampling.py
torch_so3-0.2.1.dist-info/METADATA
torch_so3-0.2.1.dist-info/WHEEL
torch_so3-0.2.1.dist-info/licenses/LICENSE
torch_so3-0.2.1.dist-info/RECORD
