Metadata-Version: 2.4
Name: torch-so3
Version: 0.2.1
Summary: Generate uniform 3D euler angles (ZYZ)
Project-URL: homepage, https://github.com/jdickerson95/torch-so3
Project-URL: repository, https://github.com/jdickerson95/torch-so3
Author-email: Josh Dickerson <jdickerson@berkeley.edu>
License: BSD-3-Clause
License-File: LICENSE
Classifier: Development Status :: 3 - Alpha
Classifier: License :: OSI Approved :: BSD License
Classifier: Programming Language :: Python :: 3
Classifier: Programming Language :: Python :: 3.9
Classifier: Programming Language :: Python :: 3.10
Classifier: Programming Language :: Python :: 3.11
Classifier: Programming Language :: Python :: 3.12
Classifier: Typing :: Typed
Requires-Python: >=3.9
Requires-Dist: healpy; platform_system != 'Windows'
Requires-Dist: numpy
Requires-Dist: torch
Provides-Extra: dev
Requires-Dist: ipython; extra == 'dev'
Requires-Dist: mypy; extra == 'dev'
Requires-Dist: pdbpp; extra == 'dev'
Requires-Dist: pre-commit; extra == 'dev'
Requires-Dist: rich; extra == 'dev'
Requires-Dist: ruff; extra == 'dev'
Provides-Extra: test
Requires-Dist: pytest; extra == 'test'
Requires-Dist: pytest-cov; extra == 'test'
